.gitignore
.travis.yml
LICENSE.txt
README.rst
requirements.txt
setup.py
docs/Makefile
docs/conf.py
docs/index.rst
docs/public.rst
docs/trading.rst
poloniex_aio/__init__.py
poloniex_aio/iter.py
poloniex_aio/public.py
poloniex_aio/trading.py
poloniex_aio.egg-info/PKG-INFO
poloniex_aio.egg-info/SOURCES.txt
poloniex_aio.egg-info/dependency_links.txt
poloniex_aio.egg-info/top_level.txt
poloniex_aio/utils/Bucket.py
tests/test_public.py