Metadata-Version: 1.2
Name: poloniex-aio
Version: 0.3.1
Summary: An async library for Poloniex api
Home-page: https://github.com/OlivierCazade/poloniex_aio
Author: Olivier Cazade
Author-email: olivier.cazade@gmail.com
License: MIT
Platform: UNKNOWN
Requires-Python: >=3.5
